[
  {
    "document_id": "DOC-00000",
    "title": "Financial Document 1",
    "category": "compliance"
  },
  {
    "document_id": "DOC-00001",
    "title": "Financial Document 2",
    "category": "treasury"
  },
  {
    "document_id": "DOC-00002",
    "title": "Financial Document 3",
    "category": "risk"
  },
  {
    "document_id": "DOC-00003",
    "title": "Financial Document 4",
    "category": "audit"
  },
  {
    "document_id": "DOC-00004",
    "title": "Financial Document 5",
    "category": "regulatory"
  },
  {
    "document_id": "DOC-00005",
    "title": "Financial Document 6",
    "category": "compliance"
  },
  {
    "document_id": "DOC-00006",
    "title": "Financial Document 7",
    "category": "treasury"
  },
  {
    "document_id": "DOC-00007",
    "title": "Financial Document 8",
    "category": "risk"
  },
  {
    "document_id": "DOC-00008",
    "title": "Financial Document 9",
    "category": "audit"
  },
  {
    "document_id": "DOC-00009",
    "title": "Financial Document 10",
    "category": "regulatory"
  },
  {
    "document_id": "DOC-00010",
    "title": "Financial Document 11",
    "category": "compliance"
  },
  {
    "document_id": "DOC-00011",
    "title": "Financial Document 12",
    "category": "treasury"
  },
  {
    "document_id": "DOC-00012",
    "title": "Financial Document 13",
    "category": "risk"
  },
  {
    "document_id": "DOC-00013",
    "title": "Financial Document 14",
    "category": "audit"
  },
  {
    "document_id": "DOC-00014",
    "title": "Financial Document 15",
    "category": "regulatory"
  },
  {
    "document_id": "DOC-00015",
    "title": "Financial Document 16",
    "category": "compliance"
  },
  {
    "document_id": "DOC-00016",
    "title": "Financial Document 17",
    "category": "treasury"
  },
  {
    "document_id": "DOC-00017",
    "title": "Financial Document 18",
    "category": "risk"
  },
  {
    "document_id": "DOC-00018",
    "title": "Financial Document 19",
    "category": "audit"
  },
  {
    "document_id": "DOC-00019",
    "title": "Financial Document 20",
    "category": "regulatory"
  },
  {
    "document_id": "DOC-00020",
    "title": "Financial Document 21",
    "category": "compliance"
  },
  {
    "document_id": "DOC-00021",
    "title": "Financial Document 22",
    "category": "treasury"
  },
  {
    "document_id": "DOC-00022",
    "title": "Financial Document 23",
    "category": "risk"
  },
  {
    "document_id": "DOC-00023",
    "title": "Financial Document 24",
    "category": "audit"
  },
  {
    "document_id": "DOC-00024",
    "title": "Financial Document 25",
    "category": "regulatory"
  },
  {
    "document_id": "DOC-00025",
    "title": "Financial Document 26",
    "category": "compliance"
  },
  {
    "document_id": "DOC-00026",
    "title": "Financial Document 27",
    "category": "treasury"
  },
  {
    "document_id": "DOC-00027",
    "title": "Financial Document 28",
    "category": "risk"
  },
  {
    "document_id": "DOC-00028",
    "title": "Financial Document 29",
    "category": "audit"
  },
  {
    "document_id": "DOC-00029",
    "title": "Financial Document 30",
    "category": "regulatory"
  },
  {
    "document_id": "DOC-00030",
    "title": "Financial Document 31",
    "category": "compliance"
  },
  {
    "document_id": "DOC-00031",
    "title": "Financial Document 32",
    "category": "treasury"
  },
  {
    "document_id": "DOC-00032",
    "title": "Financial Document 33",
    "category": "risk"
  },
  {
    "document_id": "DOC-00033",
    "title": "Financial Document 34",
    "category": "audit"
  },
  {
    "document_id": "DOC-00034",
    "title": "Financial Document 35",
    "category": "regulatory"
  },
  {
    "document_id": "DOC-00035",
    "title": "Financial Document 36",
    "category": "compliance"
  },
  {
    "document_id": "DOC-00036",
    "title": "Financial Document 37",
    "category": "treasury"
  },
  {
    "document_id": "DOC-00037",
    "title": "Financial Document 38",
    "category": "risk"
  },
  {
    "document_id": "DOC-00038",
    "title": "Financial Document 39",
    "category": "audit"
  },
  {
    "document_id": "DOC-00039",
    "title": "Financial Document 40",
    "category": "regulatory"
  },
  {
    "document_id": "DOC-00040",
    "title": "Financial Document 41",
    "category": "compliance"
  },
  {
    "document_id": "DOC-00041",
    "title": "Financial Document 42",
    "category": "treasury"
  },
  {
    "document_id": "DOC-00042",
    "title": "Financial Document 43",
    "category": "risk"
  },
  {
    "document_id": "DOC-00043",
    "title": "Financial Document 44",
    "category": "audit"
  },
  {
    "document_id": "DOC-00044",
    "title": "Financial Document 45",
    "category": "regulatory"
  },
  {
    "document_id": "DOC-00045",
    "title": "Financial Document 46",
    "category": "compliance"
  },
  {
    "document_id": "DOC-00046",
    "title": "Financial Document 47",
    "category": "treasury"
  },
  {
    "document_id": "DOC-00047",
    "title": "Financial Document 48",
    "category": "risk"
  },
  {
    "document_id": "DOC-00048",
    "title": "Financial Document 49",
    "category": "audit"
  },
  {
    "document_id": "DOC-00049",
    "title": "Financial Document 50",
    "category": "regulatory"
  },
  {
    "document_id": "DOC-00050",
    "title": "Financial Document 51",
    "category": "compliance"
  },
  {
    "document_id": "DOC-00051",
    "title": "Financial Document 52",
    "category": "treasury"
  },
  {
    "document_id": "DOC-00052",
    "title": "Financial Document 53",
    "category": "risk"
  },
  {
    "document_id": "DOC-00053",
    "title": "Financial Document 54",
    "category": "audit"
  },
  {
    "document_id": "DOC-00054",
    "title": "Financial Document 55",
    "category": "regulatory"
  },
  {
    "document_id": "DOC-00055",
    "title": "Financial Document 56",
    "category": "compliance"
  },
  {
    "document_id": "DOC-00056",
    "title": "Financial Document 57",
    "category": "treasury"
  },
  {
    "document_id": "DOC-00057",
    "title": "Financial Document 58",
    "category": "risk"
  },
  {
    "document_id": "DOC-00058",
    "title": "Financial Document 59",
    "category": "audit"
  },
  {
    "document_id": "DOC-00059",
    "title": "Financial Document 60",
    "category": "regulatory"
  },
  {
    "document_id": "DOC-00060",
    "title": "Financial Document 61",
    "category": "compliance"
  },
  {
    "document_id": "DOC-00061",
    "title": "Financial Document 62",
    "category": "treasury"
  },
  {
    "document_id": "DOC-00062",
    "title": "Financial Document 63",
    "category": "risk"
  },
  {
    "document_id": "DOC-00063",
    "title": "Financial Document 64",
    "category": "audit"
  },
  {
    "document_id": "DOC-00064",
    "title": "Financial Document 65",
    "category": "regulatory"
  },
  {
    "document_id": "DOC-00065",
    "title": "Financial Document 66",
    "category": "compliance"
  },
  {
    "document_id": "DOC-00066",
    "title": "Financial Document 67",
    "category": "treasury"
  },
  {
    "document_id": "DOC-00067",
    "title": "Financial Document 68",
    "category": "risk"
  },
  {
    "document_id": "DOC-00068",
    "title": "Financial Document 69",
    "category": "audit"
  },
  {
    "document_id": "DOC-00069",
    "title": "Financial Document 70",
    "category": "regulatory"
  },
  {
    "document_id": "DOC-00070",
    "title": "Financial Document 71",
    "category": "compliance"
  },
  {
    "document_id": "DOC-00071",
    "title": "Financial Document 72",
    "category": "treasury"
  },
  {
    "document_id": "DOC-00072",
    "title": "Financial Document 73",
    "category": "risk"
  },
  {
    "document_id": "DOC-00073",
    "title": "Financial Document 74",
    "category": "audit"
  },
  {
    "document_id": "DOC-00074",
    "title": "Financial Document 75",
    "category": "regulatory"
  },
  {
    "document_id": "DOC-00075",
    "title": "Financial Document 76",
    "category": "compliance"
  },
  {
    "document_id": "DOC-00076",
    "title": "Financial Document 77",
    "category": "treasury"
  },
  {
    "document_id": "DOC-00077",
    "title": "Financial Document 78",
    "category": "risk"
  },
  {
    "document_id": "DOC-00078",
    "title": "Financial Document 79",
    "category": "audit"
  },
  {
    "document_id": "DOC-00079",
    "title": "Financial Document 80",
    "category": "regulatory"
  },
  {
    "document_id": "DOC-00080",
    "title": "Financial Document 81",
    "category": "compliance"
  },
  {
    "document_id": "DOC-00081",
    "title": "Financial Document 82",
    "category": "treasury"
  },
  {
    "document_id": "DOC-00082",
    "title": "Financial Document 83",
    "category": "risk"
  },
  {
    "document_id": "DOC-00083",
    "title": "Financial Document 84",
    "category": "audit"
  },
  {
    "document_id": "DOC-00084",
    "title": "Financial Document 85",
    "category": "regulatory"
  },
  {
    "document_id": "DOC-00085",
    "title": "Financial Document 86",
    "category": "compliance"
  },
  {
    "document_id": "DOC-00086",
    "title": "Financial Document 87",
    "category": "treasury"
  },
  {
    "document_id": "DOC-00087",
    "title": "Financial Document 88",
    "category": "risk"
  },
  {
    "document_id": "DOC-00088",
    "title": "Financial Document 89",
    "category": "audit"
  },
  {
    "document_id": "DOC-00089",
    "title": "Financial Document 90",
    "category": "regulatory"
  },
  {
    "document_id": "DOC-00090",
    "title": "Financial Document 91",
    "category": "compliance"
  },
  {
    "document_id": "DOC-00091",
    "title": "Financial Document 92",
    "category": "treasury"
  },
  {
    "document_id": "DOC-00092",
    "title": "Financial Document 93",
    "category": "risk"
  },
  {
    "document_id": "DOC-00093",
    "title": "Financial Document 94",
    "category": "audit"
  },
  {
    "document_id": "DOC-00094",
    "title": "Financial Document 95",
    "category": "regulatory"
  },
  {
    "document_id": "DOC-00095",
    "title": "Financial Document 96",
    "category": "compliance"
  },
  {
    "document_id": "DOC-00096",
    "title": "Financial Document 97",
    "category": "treasury"
  },
  {
    "document_id": "DOC-00097",
    "title": "Financial Document 98",
    "category": "risk"
  },
  {
    "document_id": "DOC-00098",
    "title": "Financial Document 99",
    "category": "audit"
  },
  {
    "document_id": "DOC-00099",
    "title": "Financial Document 100",
    "category": "regulatory"
  },
  {
    "document_id": "DOC-00100",
    "title": "Financial Document 101",
    "category": "compliance"
  },
  {
    "document_id": "DOC-00101",
    "title": "Financial Document 102",
    "category": "treasury"
  },
  {
    "document_id": "DOC-00102",
    "title": "Financial Document 103",
    "category": "risk"
  },
  {
    "document_id": "DOC-00103",
    "title": "Financial Document 104",
    "category": "audit"
  },
  {
    "document_id": "DOC-00104",
    "title": "Financial Document 105",
    "category": "regulatory"
  },
  {
    "document_id": "DOC-00105",
    "title": "Financial Document 106",
    "category": "compliance"
  },
  {
    "document_id": "DOC-00106",
    "title": "Financial Document 107",
    "category": "treasury"
  },
  {
    "document_id": "DOC-00107",
    "title": "Financial Document 108",
    "category": "risk"
  },
  {
    "document_id": "DOC-00108",
    "title": "Financial Document 109",
    "category": "audit"
  },
  {
    "document_id": "DOC-00109",
    "title": "Financial Document 110",
    "category": "regulatory"
  },
  {
    "document_id": "DOC-00110",
    "title": "Financial Document 111",
    "category": "compliance"
  },
  {
    "document_id": "DOC-00111",
    "title": "Financial Document 112",
    "category": "treasury"
  },
  {
    "document_id": "DOC-00112",
    "title": "Financial Document 113",
    "category": "risk"
  },
  {
    "document_id": "DOC-00113",
    "title": "Financial Document 114",
    "category": "audit"
  },
  {
    "document_id": "DOC-00114",
    "title": "Financial Document 115",
    "category": "regulatory"
  },
  {
    "document_id": "DOC-00115",
    "title": "Financial Document 116",
    "category": "compliance"
  },
  {
    "document_id": "DOC-00116",
    "title": "Financial Document 117",
    "category": "treasury"
  },
  {
    "document_id": "DOC-00117",
    "title": "Financial Document 118",
    "category": "risk"
  },
  {
    "document_id": "DOC-00118",
    "title": "Financial Document 119",
    "category": "audit"
  },
  {
    "document_id": "DOC-00119",
    "title": "Financial Document 120",
    "category": "regulatory"
  },
  {
    "document_id": "DOC-00120",
    "title": "Financial Document 121",
    "category": "compliance"
  },
  {
    "document_id": "DOC-00121",
    "title": "Financial Document 122",
    "category": "treasury"
  },
  {
    "document_id": "DOC-00122",
    "title": "Financial Document 123",
    "category": "risk"
  },
  {
    "document_id": "DOC-00123",
    "title": "Financial Document 124",
    "category": "audit"
  },
  {
    "document_id": "DOC-00124",
    "title": "Financial Document 125",
    "category": "regulatory"
  },
  {
    "document_id": "DOC-00125",
    "title": "Financial Document 126",
    "category": "compliance"
  },
  {
    "document_id": "DOC-00126",
    "title": "Financial Document 127",
    "category": "treasury"
  },
  {
    "document_id": "DOC-00127",
    "title": "Financial Document 128",
    "category": "risk"
  },
  {
    "document_id": "DOC-00128",
    "title": "Financial Document 129",
    "category": "audit"
  },
  {
    "document_id": "DOC-00129",
    "title": "Financial Document 130",
    "category": "regulatory"
  },
  {
    "document_id": "DOC-00130",
    "title": "Financial Document 131",
    "category": "compliance"
  },
  {
    "document_id": "DOC-00131",
    "title": "Financial Document 132",
    "category": "treasury"
  },
  {
    "document_id": "DOC-00132",
    "title": "Financial Document 133",
    "category": "risk"
  },
  {
    "document_id": "DOC-00133",
    "title": "Financial Document 134",
    "category": "audit"
  },
  {
    "document_id": "DOC-00134",
    "title": "Financial Document 135",
    "category": "regulatory"
  },
  {
    "document_id": "DOC-00135",
    "title": "Financial Document 136",
    "category": "compliance"
  },
  {
    "document_id": "DOC-00136",
    "title": "Financial Document 137",
    "category": "treasury"
  },
  {
    "document_id": "DOC-00137",
    "title": "Financial Document 138",
    "category": "risk"
  },
  {
    "document_id": "DOC-00138",
    "title": "Financial Document 139",
    "category": "audit"
  },
  {
    "document_id": "DOC-00139",
    "title": "Financial Document 140",
    "category": "regulatory"
  },
  {
    "document_id": "DOC-00140",
    "title": "Financial Document 141",
    "category": "compliance"
  },
  {
    "document_id": "DOC-00141",
    "title": "Financial Document 142",
    "category": "treasury"
  },
  {
    "document_id": "DOC-00142",
    "title": "Financial Document 143",
    "category": "risk"
  },
  {
    "document_id": "DOC-00143",
    "title": "Financial Document 144",
    "category": "audit"
  },
  {
    "document_id": "DOC-00144",
    "title": "Financial Document 145",
    "category": "regulatory"
  },
  {
    "document_id": "DOC-00145",
    "title": "Financial Document 146",
    "category": "compliance"
  },
  {
    "document_id": "DOC-00146",
    "title": "Financial Document 147",
    "category": "treasury"
  },
  {
    "document_id": "DOC-00147",
    "title": "Financial Document 148",
    "category": "risk"
  },
  {
    "document_id": "DOC-00148",
    "title": "Financial Document 149",
    "category": "audit"
  },
  {
    "document_id": "DOC-00149",
    "title": "Financial Document 150",
    "category": "regulatory"
  },
  {
    "document_id": "DOC-00150",
    "title": "Financial Document 151",
    "category": "compliance"
  },
  {
    "document_id": "DOC-00151",
    "title": "Financial Document 152",
    "category": "treasury"
  },
  {
    "document_id": "DOC-00152",
    "title": "Financial Document 153",
    "category": "risk"
  },
  {
    "document_id": "DOC-00153",
    "title": "Financial Document 154",
    "category": "audit"
  },
  {
    "document_id": "DOC-00154",
    "title": "Financial Document 155",
    "category": "regulatory"
  },
  {
    "document_id": "DOC-00155",
    "title": "Financial Document 156",
    "category": "compliance"
  },
  {
    "document_id": "DOC-00156",
    "title": "Financial Document 157",
    "category": "treasury"
  },
  {
    "document_id": "DOC-00157",
    "title": "Financial Document 158",
    "category": "risk"
  },
  {
    "document_id": "DOC-00158",
    "title": "Financial Document 159",
    "category": "audit"
  },
  {
    "document_id": "DOC-00159",
    "title": "Financial Document 160",
    "category": "regulatory"
  },
  {
    "document_id": "DOC-00160",
    "title": "Financial Document 161",
    "category": "compliance"
  },
  {
    "document_id": "DOC-00161",
    "title": "Financial Document 162",
    "category": "treasury"
  },
  {
    "document_id": "DOC-00162",
    "title": "Financial Document 163",
    "category": "risk"
  },
  {
    "document_id": "DOC-00163",
    "title": "Financial Document 164",
    "category": "audit"
  },
  {
    "document_id": "DOC-00164",
    "title": "Financial Document 165",
    "category": "regulatory"
  },
  {
    "document_id": "DOC-00165",
    "title": "Financial Document 166",
    "category": "compliance"
  },
  {
    "document_id": "DOC-00166",
    "title": "Financial Document 167",
    "category": "treasury"
  },
  {
    "document_id": "DOC-00167",
    "title": "Financial Document 168",
    "category": "risk"
  },
  {
    "document_id": "DOC-00168",
    "title": "Financial Document 169",
    "category": "audit"
  },
  {
    "document_id": "DOC-00169",
    "title": "Financial Document 170",
    "category": "regulatory"
  },
  {
    "document_id": "DOC-00170",
    "title": "Financial Document 171",
    "category": "compliance"
  },
  {
    "document_id": "DOC-00171",
    "title": "Financial Document 172",
    "category": "treasury"
  },
  {
    "document_id": "DOC-00172",
    "title": "Financial Document 173",
    "category": "risk"
  },
  {
    "document_id": "DOC-00173",
    "title": "Financial Document 174",
    "category": "audit"
  },
  {
    "document_id": "DOC-00174",
    "title": "Financial Document 175",
    "category": "regulatory"
  },
  {
    "document_id": "DOC-00175",
    "title": "Financial Document 176",
    "category": "compliance"
  },
  {
    "document_id": "DOC-00176",
    "title": "Financial Document 177",
    "category": "treasury"
  },
  {
    "document_id": "DOC-00177",
    "title": "Financial Document 178",
    "category": "risk"
  },
  {
    "document_id": "DOC-00178",
    "title": "Financial Document 179",
    "category": "audit"
  },
  {
    "document_id": "DOC-00179",
    "title": "Financial Document 180",
    "category": "regulatory"
  },
  {
    "document_id": "DOC-00180",
    "title": "Financial Document 181",
    "category": "compliance"
  },
  {
    "document_id": "DOC-00181",
    "title": "Financial Document 182",
    "category": "treasury"
  },
  {
    "document_id": "DOC-00182",
    "title": "Financial Document 183",
    "category": "risk"
  },
  {
    "document_id": "DOC-00183",
    "title": "Financial Document 184",
    "category": "audit"
  },
  {
    "document_id": "DOC-00184",
    "title": "Financial Document 185",
    "category": "regulatory"
  },
  {
    "document_id": "DOC-00185",
    "title": "Financial Document 186",
    "category": "compliance"
  },
  {
    "document_id": "DOC-00186",
    "title": "Financial Document 187",
    "category": "treasury"
  },
  {
    "document_id": "DOC-00187",
    "title": "Financial Document 188",
    "category": "risk"
  },
  {
    "document_id": "DOC-00188",
    "title": "Financial Document 189",
    "category": "audit"
  },
  {
    "document_id": "DOC-00189",
    "title": "Financial Document 190",
    "category": "regulatory"
  },
  {
    "document_id": "DOC-00190",
    "title": "Financial Document 191",
    "category": "compliance"
  },
  {
    "document_id": "DOC-00191",
    "title": "Financial Document 192",
    "category": "treasury"
  },
  {
    "document_id": "DOC-00192",
    "title": "Financial Document 193",
    "category": "risk"
  },
  {
    "document_id": "DOC-00193",
    "title": "Financial Document 194",
    "category": "audit"
  },
  {
    "document_id": "DOC-00194",
    "title": "Financial Document 195",
    "category": "regulatory"
  },
  {
    "document_id": "DOC-00195",
    "title": "Financial Document 196",
    "category": "compliance"
  },
  {
    "document_id": "DOC-00196",
    "title": "Financial Document 197",
    "category": "treasury"
  },
  {
    "document_id": "DOC-00197",
    "title": "Financial Document 198",
    "category": "risk"
  },
  {
    "document_id": "DOC-00198",
    "title": "Financial Document 199",
    "category": "audit"
  },
  {
    "document_id": "DOC-00199",
    "title": "Financial Document 200",
    "category": "regulatory"
  },
  {
    "document_id": "DOC-00200",
    "title": "Financial Document 201",
    "category": "compliance"
  },
  {
    "document_id": "DOC-00201",
    "title": "Financial Document 202",
    "category": "treasury"
  },
  {
    "document_id": "DOC-00202",
    "title": "Financial Document 203",
    "category": "risk"
  },
  {
    "document_id": "DOC-00203",
    "title": "Financial Document 204",
    "category": "audit"
  },
  {
    "document_id": "DOC-00204",
    "title": "Financial Document 205",
    "category": "regulatory"
  },
  {
    "document_id": "DOC-00205",
    "title": "Financial Document 206",
    "category": "compliance"
  },
  {
    "document_id": "DOC-00206",
    "title": "Financial Document 207",
    "category": "treasury"
  },
  {
    "document_id": "DOC-00207",
    "title": "Financial Document 208",
    "category": "risk"
  },
  {
    "document_id": "DOC-00208",
    "title": "Financial Document 209",
    "category": "audit"
  },
  {
    "document_id": "DOC-00209",
    "title": "Financial Document 210",
    "category": "regulatory"
  },
  {
    "document_id": "DOC-00210",
    "title": "Financial Document 211",
    "category": "compliance"
  },
  {
    "document_id": "DOC-00211",
    "title": "Financial Document 212",
    "category": "treasury"
  },
  {
    "document_id": "DOC-00212",
    "title": "Financial Document 213",
    "category": "risk"
  },
  {
    "document_id": "DOC-00213",
    "title": "Financial Document 214",
    "category": "audit"
  },
  {
    "document_id": "DOC-00214",
    "title": "Financial Document 215",
    "category": "regulatory"
  },
  {
    "document_id": "DOC-00215",
    "title": "Financial Document 216",
    "category": "compliance"
  },
  {
    "document_id": "DOC-00216",
    "title": "Financial Document 217",
    "category": "treasury"
  },
  {
    "document_id": "DOC-00217",
    "title": "Financial Document 218",
    "category": "risk"
  },
  {
    "document_id": "DOC-00218",
    "title": "Financial Document 219",
    "category": "audit"
  },
  {
    "document_id": "DOC-00219",
    "title": "Financial Document 220",
    "category": "regulatory"
  },
  {
    "document_id": "DOC-00220",
    "title": "Financial Document 221",
    "category": "compliance"
  },
  {
    "document_id": "DOC-00221",
    "title": "Financial Document 222",
    "category": "treasury"
  },
  {
    "document_id": "DOC-00222",
    "title": "Financial Document 223",
    "category": "risk"
  },
  {
    "document_id": "DOC-00223",
    "title": "Financial Document 224",
    "category": "audit"
  },
  {
    "document_id": "DOC-00224",
    "title": "Financial Document 225",
    "category": "regulatory"
  },
  {
    "document_id": "DOC-00225",
    "title": "Financial Document 226",
    "category": "compliance"
  },
  {
    "document_id": "DOC-00226",
    "title": "Financial Document 227",
    "category": "treasury"
  },
  {
    "document_id": "DOC-00227",
    "title": "Financial Document 228",
    "category": "risk"
  },
  {
    "document_id": "DOC-00228",
    "title": "Financial Document 229",
    "category": "audit"
  },
  {
    "document_id": "DOC-00229",
    "title": "Financial Document 230",
    "category": "regulatory"
  },
  {
    "document_id": "DOC-00230",
    "title": "Financial Document 231",
    "category": "compliance"
  },
  {
    "document_id": "DOC-00231",
    "title": "Financial Document 232",
    "category": "treasury"
  },
  {
    "document_id": "DOC-00232",
    "title": "Financial Document 233",
    "category": "risk"
  },
  {
    "document_id": "DOC-00233",
    "title": "Financial Document 234",
    "category": "audit"
  },
  {
    "document_id": "DOC-00234",
    "title": "Financial Document 235",
    "category": "regulatory"
  },
  {
    "document_id": "DOC-00235",
    "title": "Financial Document 236",
    "category": "compliance"
  },
  {
    "document_id": "DOC-00236",
    "title": "Financial Document 237",
    "category": "treasury"
  },
  {
    "document_id": "DOC-00237",
    "title": "Financial Document 238",
    "category": "risk"
  },
  {
    "document_id": "DOC-00238",
    "title": "Financial Document 239",
    "category": "audit"
  },
  {
    "document_id": "DOC-00239",
    "title": "Financial Document 240",
    "category": "regulatory"
  },
  {
    "document_id": "DOC-00240",
    "title": "Financial Document 241",
    "category": "compliance"
  },
  {
    "document_id": "DOC-00241",
    "title": "Financial Document 242",
    "category": "treasury"
  },
  {
    "document_id": "DOC-00242",
    "title": "Financial Document 243",
    "category": "risk"
  },
  {
    "document_id": "DOC-00243",
    "title": "Financial Document 244",
    "category": "audit"
  },
  {
    "document_id": "DOC-00244",
    "title": "Financial Document 245",
    "category": "regulatory"
  },
  {
    "document_id": "DOC-00245",
    "title": "Financial Document 246",
    "category": "compliance"
  },
  {
    "document_id": "DOC-00246",
    "title": "Financial Document 247",
    "category": "treasury"
  },
  {
    "document_id": "DOC-00247",
    "title": "Financial Document 248",
    "category": "risk"
  },
  {
    "document_id": "DOC-00248",
    "title": "Financial Document 249",
    "category": "audit"
  },
  {
    "document_id": "DOC-00249",
    "title": "Financial Document 250",
    "category": "regulatory"
  },
  {
    "document_id": "DOC-00250",
    "title": "Financial Document 251",
    "category": "compliance"
  },
  {
    "document_id": "DOC-00251",
    "title": "Financial Document 252",
    "category": "treasury"
  },
  {
    "document_id": "DOC-00252",
    "title": "Financial Document 253",
    "category": "risk"
  },
  {
    "document_id": "DOC-00253",
    "title": "Financial Document 254",
    "category": "audit"
  },
  {
    "document_id": "DOC-00254",
    "title": "Financial Document 255",
    "category": "regulatory"
  },
  {
    "document_id": "DOC-00255",
    "title": "Financial Document 256",
    "category": "compliance"
  },
  {
    "document_id": "DOC-00256",
    "title": "Financial Document 257",
    "category": "treasury"
  },
  {
    "document_id": "DOC-00257",
    "title": "Financial Document 258",
    "category": "risk"
  },
  {
    "document_id": "DOC-00258",
    "title": "Financial Document 259",
    "category": "audit"
  },
  {
    "document_id": "DOC-00259",
    "title": "Financial Document 260",
    "category": "regulatory"
  },
  {
    "document_id": "DOC-00260",
    "title": "Financial Document 261",
    "category": "compliance"
  },
  {
    "document_id": "DOC-00261",
    "title": "Financial Document 262",
    "category": "treasury"
  },
  {
    "document_id": "DOC-00262",
    "title": "Financial Document 263",
    "category": "risk"
  },
  {
    "document_id": "DOC-00263",
    "title": "Financial Document 264",
    "category": "audit"
  },
  {
    "document_id": "DOC-00264",
    "title": "Financial Document 265",
    "category": "regulatory"
  },
  {
    "document_id": "DOC-00265",
    "title": "Financial Document 266",
    "category": "compliance"
  },
  {
    "document_id": "DOC-00266",
    "title": "Financial Document 267",
    "category": "treasury"
  },
  {
    "document_id": "DOC-00267",
    "title": "Financial Document 268",
    "category": "risk"
  },
  {
    "document_id": "DOC-00268",
    "title": "Financial Document 269",
    "category": "audit"
  },
  {
    "document_id": "DOC-00269",
    "title": "Financial Document 270",
    "category": "regulatory"
  },
  {
    "document_id": "DOC-00270",
    "title": "Financial Document 271",
    "category": "compliance"
  },
  {
    "document_id": "DOC-00271",
    "title": "Financial Document 272",
    "category": "treasury"
  },
  {
    "document_id": "DOC-00272",
    "title": "Financial Document 273",
    "category": "risk"
  },
  {
    "document_id": "DOC-00273",
    "title": "Financial Document 274",
    "category": "audit"
  },
  {
    "document_id": "DOC-00274",
    "title": "Financial Document 275",
    "category": "regulatory"
  },
  {
    "document_id": "DOC-00275",
    "title": "Financial Document 276",
    "category": "compliance"
  },
  {
    "document_id": "DOC-00276",
    "title": "Financial Document 277",
    "category": "treasury"
  },
  {
    "document_id": "DOC-00277",
    "title": "Financial Document 278",
    "category": "risk"
  },
  {
    "document_id": "DOC-00278",
    "title": "Financial Document 279",
    "category": "audit"
  },
  {
    "document_id": "DOC-00279",
    "title": "Financial Document 280",
    "category": "regulatory"
  },
  {
    "document_id": "DOC-00280",
    "title": "Financial Document 281",
    "category": "compliance"
  },
  {
    "document_id": "DOC-00281",
    "title": "Financial Document 282",
    "category": "treasury"
  },
  {
    "document_id": "DOC-00282",
    "title": "Financial Document 283",
    "category": "risk"
  },
  {
    "document_id": "DOC-00283",
    "title": "Financial Document 284",
    "category": "audit"
  },
  {
    "document_id": "DOC-00284",
    "title": "Financial Document 285",
    "category": "regulatory"
  },
  {
    "document_id": "DOC-00285",
    "title": "Financial Document 286",
    "category": "compliance"
  },
  {
    "document_id": "DOC-00286",
    "title": "Financial Document 287",
    "category": "treasury"
  },
  {
    "document_id": "DOC-00287",
    "title": "Financial Document 288",
    "category": "risk"
  },
  {
    "document_id": "DOC-00288",
    "title": "Financial Document 289",
    "category": "audit"
  },
  {
    "document_id": "DOC-00289",
    "title": "Financial Document 290",
    "category": "regulatory"
  },
  {
    "document_id": "DOC-00290",
    "title": "Financial Document 291",
    "category": "compliance"
  },
  {
    "document_id": "DOC-00291",
    "title": "Financial Document 292",
    "category": "treasury"
  },
  {
    "document_id": "DOC-00292",
    "title": "Financial Document 293",
    "category": "risk"
  },
  {
    "document_id": "DOC-00293",
    "title": "Financial Document 294",
    "category": "audit"
  },
  {
    "document_id": "DOC-00294",
    "title": "Financial Document 295",
    "category": "regulatory"
  },
  {
    "document_id": "DOC-00295",
    "title": "Financial Document 296",
    "category": "compliance"
  },
  {
    "document_id": "DOC-00296",
    "title": "Financial Document 297",
    "category": "treasury"
  },
  {
    "document_id": "DOC-00297",
    "title": "Financial Document 298",
    "category": "risk"
  },
  {
    "document_id": "DOC-00298",
    "title": "Financial Document 299",
    "category": "audit"
  },
  {
    "document_id": "DOC-00299",
    "title": "Financial Document 300",
    "category": "regulatory"
  },
  {
    "document_id": "DOC-00300",
    "title": "Financial Document 301",
    "category": "compliance"
  },
  {
    "document_id": "DOC-00301",
    "title": "Financial Document 302",
    "category": "treasury"
  },
  {
    "document_id": "DOC-00302",
    "title": "Financial Document 303",
    "category": "risk"
  },
  {
    "document_id": "DOC-00303",
    "title": "Financial Document 304",
    "category": "audit"
  },
  {
    "document_id": "DOC-00304",
    "title": "Financial Document 305",
    "category": "regulatory"
  },
  {
    "document_id": "DOC-00305",
    "title": "Financial Document 306",
    "category": "compliance"
  },
  {
    "document_id": "DOC-00306",
    "title": "Financial Document 307",
    "category": "treasury"
  },
  {
    "document_id": "DOC-00307",
    "title": "Financial Document 308",
    "category": "risk"
  },
  {
    "document_id": "DOC-00308",
    "title": "Financial Document 309",
    "category": "audit"
  },
  {
    "document_id": "DOC-00309",
    "title": "Financial Document 310",
    "category": "regulatory"
  },
  {
    "document_id": "DOC-00310",
    "title": "Financial Document 311",
    "category": "compliance"
  },
  {
    "document_id": "DOC-00311",
    "title": "Financial Document 312",
    "category": "treasury"
  },
  {
    "document_id": "DOC-00312",
    "title": "Financial Document 313",
    "category": "risk"
  },
  {
    "document_id": "DOC-00313",
    "title": "Financial Document 314",
    "category": "audit"
  },
  {
    "document_id": "DOC-00314",
    "title": "Financial Document 315",
    "category": "regulatory"
  },
  {
    "document_id": "DOC-00315",
    "title": "Financial Document 316",
    "category": "compliance"
  },
  {
    "document_id": "DOC-00316",
    "title": "Financial Document 317",
    "category": "treasury"
  },
  {
    "document_id": "DOC-00317",
    "title": "Financial Document 318",
    "category": "risk"
  },
  {
    "document_id": "DOC-00318",
    "title": "Financial Document 319",
    "category": "audit"
  },
  {
    "document_id": "DOC-00319",
    "title": "Financial Document 320",
    "category": "regulatory"
  },
  {
    "document_id": "DOC-00320",
    "title": "Financial Document 321",
    "category": "compliance"
  },
  {
    "document_id": "DOC-00321",
    "title": "Financial Document 322",
    "category": "treasury"
  },
  {
    "document_id": "DOC-00322",
    "title": "Financial Document 323",
    "category": "risk"
  },
  {
    "document_id": "DOC-00323",
    "title": "Financial Document 324",
    "category": "audit"
  },
  {
    "document_id": "DOC-00324",
    "title": "Financial Document 325",
    "category": "regulatory"
  },
  {
    "document_id": "DOC-00325",
    "title": "Financial Document 326",
    "category": "compliance"
  },
  {
    "document_id": "DOC-00326",
    "title": "Financial Document 327",
    "category": "treasury"
  },
  {
    "document_id": "DOC-00327",
    "title": "Financial Document 328",
    "category": "risk"
  },
  {
    "document_id": "DOC-00328",
    "title": "Financial Document 329",
    "category": "audit"
  },
  {
    "document_id": "DOC-00329",
    "title": "Financial Document 330",
    "category": "regulatory"
  },
  {
    "document_id": "DOC-00330",
    "title": "Financial Document 331",
    "category": "compliance"
  },
  {
    "document_id": "DOC-00331",
    "title": "Financial Document 332",
    "category": "treasury"
  },
  {
    "document_id": "DOC-00332",
    "title": "Financial Document 333",
    "category": "risk"
  },
  {
    "document_id": "DOC-00333",
    "title": "Financial Document 334",
    "category": "audit"
  },
  {
    "document_id": "DOC-00334",
    "title": "Financial Document 335",
    "category": "regulatory"
  },
  {
    "document_id": "DOC-00335",
    "title": "Financial Document 336",
    "category": "compliance"
  },
  {
    "document_id": "DOC-00336",
    "title": "Financial Document 337",
    "category": "treasury"
  },
  {
    "document_id": "DOC-00337",
    "title": "Financial Document 338",
    "category": "risk"
  },
  {
    "document_id": "DOC-00338",
    "title": "Financial Document 339",
    "category": "audit"
  },
  {
    "document_id": "DOC-00339",
    "title": "Financial Document 340",
    "category": "regulatory"
  },
  {
    "document_id": "DOC-00340",
    "title": "Financial Document 341",
    "category": "compliance"
  },
  {
    "document_id": "DOC-00341",
    "title": "Financial Document 342",
    "category": "treasury"
  },
  {
    "document_id": "DOC-00342",
    "title": "Financial Document 343",
    "category": "risk"
  },
  {
    "document_id": "DOC-00343",
    "title": "Financial Document 344",
    "category": "audit"
  },
  {
    "document_id": "DOC-00344",
    "title": "Financial Document 345",
    "category": "regulatory"
  },
  {
    "document_id": "DOC-00345",
    "title": "Financial Document 346",
    "category": "compliance"
  },
  {
    "document_id": "DOC-00346",
    "title": "Financial Document 347",
    "category": "treasury"
  },
  {
    "document_id": "DOC-00347",
    "title": "Financial Document 348",
    "category": "risk"
  },
  {
    "document_id": "DOC-00348",
    "title": "Financial Document 349",
    "category": "audit"
  },
  {
    "document_id": "DOC-00349",
    "title": "Financial Document 350",
    "category": "regulatory"
  },
  {
    "document_id": "DOC-00350",
    "title": "Financial Document 351",
    "category": "compliance"
  },
  {
    "document_id": "DOC-00351",
    "title": "Financial Document 352",
    "category": "treasury"
  },
  {
    "document_id": "DOC-00352",
    "title": "Financial Document 353",
    "category": "risk"
  },
  {
    "document_id": "DOC-00353",
    "title": "Financial Document 354",
    "category": "audit"
  },
  {
    "document_id": "DOC-00354",
    "title": "Financial Document 355",
    "category": "regulatory"
  },
  {
    "document_id": "DOC-00355",
    "title": "Financial Document 356",
    "category": "compliance"
  },
  {
    "document_id": "DOC-00356",
    "title": "Financial Document 357",
    "category": "treasury"
  },
  {
    "document_id": "DOC-00357",
    "title": "Financial Document 358",
    "category": "risk"
  },
  {
    "document_id": "DOC-00358",
    "title": "Financial Document 359",
    "category": "audit"
  },
  {
    "document_id": "DOC-00359",
    "title": "Financial Document 360",
    "category": "regulatory"
  },
  {
    "document_id": "DOC-00360",
    "title": "Financial Document 361",
    "category": "compliance"
  },
  {
    "document_id": "DOC-00361",
    "title": "Financial Document 362",
    "category": "treasury"
  },
  {
    "document_id": "DOC-00362",
    "title": "Financial Document 363",
    "category": "risk"
  },
  {
    "document_id": "DOC-00363",
    "title": "Financial Document 364",
    "category": "audit"
  },
  {
    "document_id": "DOC-00364",
    "title": "Financial Document 365",
    "category": "regulatory"
  },
  {
    "document_id": "DOC-00365",
    "title": "Financial Document 366",
    "category": "compliance"
  },
  {
    "document_id": "DOC-00366",
    "title": "Financial Document 367",
    "category": "treasury"
  },
  {
    "document_id": "DOC-00367",
    "title": "Financial Document 368",
    "category": "risk"
  },
  {
    "document_id": "DOC-00368",
    "title": "Financial Document 369",
    "category": "audit"
  },
  {
    "document_id": "DOC-00369",
    "title": "Financial Document 370",
    "category": "regulatory"
  },
  {
    "document_id": "DOC-00370",
    "title": "Financial Document 371",
    "category": "compliance"
  },
  {
    "document_id": "DOC-00371",
    "title": "Financial Document 372",
    "category": "treasury"
  },
  {
    "document_id": "DOC-00372",
    "title": "Financial Document 373",
    "category": "risk"
  },
  {
    "document_id": "DOC-00373",
    "title": "Financial Document 374",
    "category": "audit"
  },
  {
    "document_id": "DOC-00374",
    "title": "Financial Document 375",
    "category": "regulatory"
  },
  {
    "document_id": "DOC-00375",
    "title": "Financial Document 376",
    "category": "compliance"
  },
  {
    "document_id": "DOC-00376",
    "title": "Financial Document 377",
    "category": "treasury"
  },
  {
    "document_id": "DOC-00377",
    "title": "Financial Document 378",
    "category": "risk"
  },
  {
    "document_id": "DOC-00378",
    "title": "Financial Document 379",
    "category": "audit"
  },
  {
    "document_id": "DOC-00379",
    "title": "Financial Document 380",
    "category": "regulatory"
  },
  {
    "document_id": "DOC-00380",
    "title": "Financial Document 381",
    "category": "compliance"
  },
  {
    "document_id": "DOC-00381",
    "title": "Financial Document 382",
    "category": "treasury"
  },
  {
    "document_id": "DOC-00382",
    "title": "Financial Document 383",
    "category": "risk"
  },
  {
    "document_id": "DOC-00383",
    "title": "Financial Document 384",
    "category": "audit"
  },
  {
    "document_id": "DOC-00384",
    "title": "Financial Document 385",
    "category": "regulatory"
  },
  {
    "document_id": "DOC-00385",
    "title": "Financial Document 386",
    "category": "compliance"
  },
  {
    "document_id": "DOC-00386",
    "title": "Financial Document 387",
    "category": "treasury"
  },
  {
    "document_id": "DOC-00387",
    "title": "Financial Document 388",
    "category": "risk"
  },
  {
    "document_id": "DOC-00388",
    "title": "Financial Document 389",
    "category": "audit"
  },
  {
    "document_id": "DOC-00389",
    "title": "Financial Document 390",
    "category": "regulatory"
  },
  {
    "document_id": "DOC-00390",
    "title": "Financial Document 391",
    "category": "compliance"
  },
  {
    "document_id": "DOC-00391",
    "title": "Financial Document 392",
    "category": "treasury"
  },
  {
    "document_id": "DOC-00392",
    "title": "Financial Document 393",
    "category": "risk"
  },
  {
    "document_id": "DOC-00393",
    "title": "Financial Document 394",
    "category": "audit"
  },
  {
    "document_id": "DOC-00394",
    "title": "Financial Document 395",
    "category": "regulatory"
  },
  {
    "document_id": "DOC-00395",
    "title": "Financial Document 396",
    "category": "compliance"
  },
  {
    "document_id": "DOC-00396",
    "title": "Financial Document 397",
    "category": "treasury"
  },
  {
    "document_id": "DOC-00397",
    "title": "Financial Document 398",
    "category": "risk"
  },
  {
    "document_id": "DOC-00398",
    "title": "Financial Document 399",
    "category": "audit"
  },
  {
    "document_id": "DOC-00399",
    "title": "Financial Document 400",
    "category": "regulatory"
  },
  {
    "document_id": "DOC-00400",
    "title": "Financial Document 401",
    "category": "compliance"
  },
  {
    "document_id": "DOC-00401",
    "title": "Financial Document 402",
    "category": "treasury"
  },
  {
    "document_id": "DOC-00402",
    "title": "Financial Document 403",
    "category": "risk"
  },
  {
    "document_id": "DOC-00403",
    "title": "Financial Document 404",
    "category": "audit"
  },
  {
    "document_id": "DOC-00404",
    "title": "Financial Document 405",
    "category": "regulatory"
  },
  {
    "document_id": "DOC-00405",
    "title": "Financial Document 406",
    "category": "compliance"
  },
  {
    "document_id": "DOC-00406",
    "title": "Financial Document 407",
    "category": "treasury"
  },
  {
    "document_id": "DOC-00407",
    "title": "Financial Document 408",
    "category": "risk"
  },
  {
    "document_id": "DOC-00408",
    "title": "Financial Document 409",
    "category": "audit"
  },
  {
    "document_id": "DOC-00409",
    "title": "Financial Document 410",
    "category": "regulatory"
  },
  {
    "document_id": "DOC-00410",
    "title": "Financial Document 411",
    "category": "compliance"
  },
  {
    "document_id": "DOC-00411",
    "title": "Financial Document 412",
    "category": "treasury"
  },
  {
    "document_id": "DOC-00412",
    "title": "Financial Document 413",
    "category": "risk"
  },
  {
    "document_id": "DOC-00413",
    "title": "Financial Document 414",
    "category": "audit"
  },
  {
    "document_id": "DOC-00414",
    "title": "Financial Document 415",
    "category": "regulatory"
  },
  {
    "document_id": "DOC-00415",
    "title": "Financial Document 416",
    "category": "compliance"
  },
  {
    "document_id": "DOC-00416",
    "title": "Financial Document 417",
    "category": "treasury"
  },
  {
    "document_id": "DOC-00417",
    "title": "Financial Document 418",
    "category": "risk"
  },
  {
    "document_id": "DOC-00418",
    "title": "Financial Document 419",
    "category": "audit"
  },
  {
    "document_id": "DOC-00419",
    "title": "Financial Document 420",
    "category": "regulatory"
  },
  {
    "document_id": "DOC-00420",
    "title": "Financial Document 421",
    "category": "compliance"
  },
  {
    "document_id": "DOC-00421",
    "title": "Financial Document 422",
    "category": "treasury"
  },
  {
    "document_id": "DOC-00422",
    "title": "Financial Document 423",
    "category": "risk"
  },
  {
    "document_id": "DOC-00423",
    "title": "Financial Document 424",
    "category": "audit"
  },
  {
    "document_id": "DOC-00424",
    "title": "Financial Document 425",
    "category": "regulatory"
  },
  {
    "document_id": "DOC-00425",
    "title": "Financial Document 426",
    "category": "compliance"
  },
  {
    "document_id": "DOC-00426",
    "title": "Financial Document 427",
    "category": "treasury"
  },
  {
    "document_id": "DOC-00427",
    "title": "Financial Document 428",
    "category": "risk"
  },
  {
    "document_id": "DOC-00428",
    "title": "Financial Document 429",
    "category": "audit"
  },
  {
    "document_id": "DOC-00429",
    "title": "Financial Document 430",
    "category": "regulatory"
  },
  {
    "document_id": "DOC-00430",
    "title": "Financial Document 431",
    "category": "compliance"
  },
  {
    "document_id": "DOC-00431",
    "title": "Financial Document 432",
    "category": "treasury"
  },
  {
    "document_id": "DOC-00432",
    "title": "Financial Document 433",
    "category": "risk"
  },
  {
    "document_id": "DOC-00433",
    "title": "Financial Document 434",
    "category": "audit"
  },
  {
    "document_id": "DOC-00434",
    "title": "Financial Document 435",
    "category": "regulatory"
  },
  {
    "document_id": "DOC-00435",
    "title": "Financial Document 436",
    "category": "compliance"
  },
  {
    "document_id": "DOC-00436",
    "title": "Financial Document 437",
    "category": "treasury"
  },
  {
    "document_id": "DOC-00437",
    "title": "Financial Document 438",
    "category": "risk"
  },
  {
    "document_id": "DOC-00438",
    "title": "Financial Document 439",
    "category": "audit"
  },
  {
    "document_id": "DOC-00439",
    "title": "Financial Document 440",
    "category": "regulatory"
  },
  {
    "document_id": "DOC-00440",
    "title": "Financial Document 441",
    "category": "compliance"
  },
  {
    "document_id": "DOC-00441",
    "title": "Financial Document 442",
    "category": "treasury"
  },
  {
    "document_id": "DOC-00442",
    "title": "Financial Document 443",
    "category": "risk"
  },
  {
    "document_id": "DOC-00443",
    "title": "Financial Document 444",
    "category": "audit"
  },
  {
    "document_id": "DOC-00444",
    "title": "Financial Document 445",
    "category": "regulatory"
  },
  {
    "document_id": "DOC-00445",
    "title": "Financial Document 446",
    "category": "compliance"
  },
  {
    "document_id": "DOC-00446",
    "title": "Financial Document 447",
    "category": "treasury"
  },
  {
    "document_id": "DOC-00447",
    "title": "Financial Document 448",
    "category": "risk"
  },
  {
    "document_id": "DOC-00448",
    "title": "Financial Document 449",
    "category": "audit"
  },
  {
    "document_id": "DOC-00449",
    "title": "Financial Document 450",
    "category": "regulatory"
  },
  {
    "document_id": "DOC-00450",
    "title": "Financial Document 451",
    "category": "compliance"
  },
  {
    "document_id": "DOC-00451",
    "title": "Financial Document 452",
    "category": "treasury"
  },
  {
    "document_id": "DOC-00452",
    "title": "Financial Document 453",
    "category": "risk"
  },
  {
    "document_id": "DOC-00453",
    "title": "Financial Document 454",
    "category": "audit"
  },
  {
    "document_id": "DOC-00454",
    "title": "Financial Document 455",
    "category": "regulatory"
  },
  {
    "document_id": "DOC-00455",
    "title": "Financial Document 456",
    "category": "compliance"
  },
  {
    "document_id": "DOC-00456",
    "title": "Financial Document 457",
    "category": "treasury"
  },
  {
    "document_id": "DOC-00457",
    "title": "Financial Document 458",
    "category": "risk"
  },
  {
    "document_id": "DOC-00458",
    "title": "Financial Document 459",
    "category": "audit"
  },
  {
    "document_id": "DOC-00459",
    "title": "Financial Document 460",
    "category": "regulatory"
  },
  {
    "document_id": "DOC-00460",
    "title": "Financial Document 461",
    "category": "compliance"
  },
  {
    "document_id": "DOC-00461",
    "title": "Financial Document 462",
    "category": "treasury"
  },
  {
    "document_id": "DOC-00462",
    "title": "Financial Document 463",
    "category": "risk"
  },
  {
    "document_id": "DOC-00463",
    "title": "Financial Document 464",
    "category": "audit"
  },
  {
    "document_id": "DOC-00464",
    "title": "Financial Document 465",
    "category": "regulatory"
  },
  {
    "document_id": "DOC-00465",
    "title": "Financial Document 466",
    "category": "compliance"
  },
  {
    "document_id": "DOC-00466",
    "title": "Financial Document 467",
    "category": "treasury"
  },
  {
    "document_id": "DOC-00467",
    "title": "Financial Document 468",
    "category": "risk"
  },
  {
    "document_id": "DOC-00468",
    "title": "Financial Document 469",
    "category": "audit"
  },
  {
    "document_id": "DOC-00469",
    "title": "Financial Document 470",
    "category": "regulatory"
  },
  {
    "document_id": "DOC-00470",
    "title": "Financial Document 471",
    "category": "compliance"
  },
  {
    "document_id": "DOC-00471",
    "title": "Financial Document 472",
    "category": "treasury"
  },
  {
    "document_id": "DOC-00472",
    "title": "Financial Document 473",
    "category": "risk"
  },
  {
    "document_id": "DOC-00473",
    "title": "Financial Document 474",
    "category": "audit"
  },
  {
    "document_id": "DOC-00474",
    "title": "Financial Document 475",
    "category": "regulatory"
  },
  {
    "document_id": "DOC-00475",
    "title": "Financial Document 476",
    "category": "compliance"
  },
  {
    "document_id": "DOC-00476",
    "title": "Financial Document 477",
    "category": "treasury"
  },
  {
    "document_id": "DOC-00477",
    "title": "Financial Document 478",
    "category": "risk"
  },
  {
    "document_id": "DOC-00478",
    "title": "Financial Document 479",
    "category": "audit"
  },
  {
    "document_id": "DOC-00479",
    "title": "Financial Document 480",
    "category": "regulatory"
  },
  {
    "document_id": "DOC-00480",
    "title": "Financial Document 481",
    "category": "compliance"
  },
  {
    "document_id": "DOC-00481",
    "title": "Financial Document 482",
    "category": "treasury"
  },
  {
    "document_id": "DOC-00482",
    "title": "Financial Document 483",
    "category": "risk"
  },
  {
    "document_id": "DOC-00483",
    "title": "Financial Document 484",
    "category": "audit"
  },
  {
    "document_id": "DOC-00484",
    "title": "Financial Document 485",
    "category": "regulatory"
  },
  {
    "document_id": "DOC-00485",
    "title": "Financial Document 486",
    "category": "compliance"
  },
  {
    "document_id": "DOC-00486",
    "title": "Financial Document 487",
    "category": "treasury"
  },
  {
    "document_id": "DOC-00487",
    "title": "Financial Document 488",
    "category": "risk"
  },
  {
    "document_id": "DOC-00488",
    "title": "Financial Document 489",
    "category": "audit"
  },
  {
    "document_id": "DOC-00489",
    "title": "Financial Document 490",
    "category": "regulatory"
  },
  {
    "document_id": "DOC-00490",
    "title": "Financial Document 491",
    "category": "compliance"
  },
  {
    "document_id": "DOC-00491",
    "title": "Financial Document 492",
    "category": "treasury"
  },
  {
    "document_id": "DOC-00492",
    "title": "Financial Document 493",
    "category": "risk"
  },
  {
    "document_id": "DOC-00493",
    "title": "Financial Document 494",
    "category": "audit"
  },
  {
    "document_id": "DOC-00494",
    "title": "Financial Document 495",
    "category": "regulatory"
  },
  {
    "document_id": "DOC-00495",
    "title": "Financial Document 496",
    "category": "compliance"
  },
  {
    "document_id": "DOC-00496",
    "title": "Financial Document 497",
    "category": "treasury"
  },
  {
    "document_id": "DOC-00497",
    "title": "Financial Document 498",
    "category": "risk"
  },
  {
    "document_id": "DOC-00498",
    "title": "Financial Document 499",
    "category": "audit"
  },
  {
    "document_id": "DOC-00499",
    "title": "Financial Document 500",
    "category": "regulatory"
  }
]